{"nodes": [{"id": "temp_openagentscontrol_packages_cli_src_lib_sha256_ts", "label": "sha256.ts", "file_type": "code", "source_file": "%TEMP%\\OpenAgentsControl\\packages\\cli\\src\\lib\\sha256.ts", "source_location": "L1"}, {"id": "sha256_computefilehash", "label": "computeFileHash()", "file_type": "code", "source_file": "%TEMP%\\OpenAgentsControl\\packages\\cli\\src\\lib\\sha256.ts", "source_location": "L4"}, {"id": "sha256_computestringhash", "label": "computeStringHash()", "file_type": "code", "source_file": "%TEMP%\\OpenAgentsControl\\packages\\cli\\src\\lib\\sha256.ts", "source_location": "L15"}, {"id": "sha256_hashesmatch", "label": "hashesMatch()", "file_type": "code", "source_file": "%TEMP%\\OpenAgentsControl\\packages\\cli\\src\\lib\\sha256.ts", "source_location": "L20"}], "edges": [{"source": "temp_openagentscontrol_packages_cli_src_lib_sha256_ts", "target": "node_crypto", "relation": "imports_from", "confidence": "EXTRACTED", "source_file": "%TEMP%\\OpenAgentsControl\\packages\\cli\\src\\lib\\sha256.ts", "source_location": "L1", "weight": 1.0}, {"source": "temp_openagentscontrol_packages_cli_src_lib_sha256_ts", "target": "sha256_computefilehash", "relation": "contains", "confidence": "EXTRACTED", "source_file": "%TEMP%\\OpenAgentsControl\\packages\\cli\\src\\lib\\sha256.ts", "source_location": "L4", "weight": 1.0}, {"source": "temp_openagentscontrol_packages_cli_src_lib_sha256_ts", "target": "sha256_computestringhash", "relation": "contains", "confidence": "EXTRACTED", "source_file": "%TEMP%\\OpenAgentsControl\\packages\\cli\\src\\lib\\sha256.ts", "source_location": "L15", "weight": 1.0}, {"source": "temp_openagentscontrol_packages_cli_src_lib_sha256_ts", "target": "sha256_hashesmatch", "relation": "contains", "confidence": "EXTRACTED", "source_file": "%TEMP%\\OpenAgentsControl\\packages\\cli\\src\\lib\\sha256.ts", "source_location": "L20", "weight": 1.0}]}