{"nodes": [{"id": "src_lib_online_satellite_ts", "label": "satellite.ts", "file_type": "code", "source_file": "src\\lib\\online\\satellite.ts", "source_location": "L1"}, {"id": "satellite_getimagerylayers", "label": "getImageryLayers()", "file_type": "code", "source_file": "src\\lib\\online\\satellite.ts", "source_location": "L73"}, {"id": "satellite_getimageryforlocation", "label": "getImageryForLocation()", "file_type": "code", "source_file": "src\\lib\\online\\satellite.ts", "source_location": "L85"}, {"id": "satellite_getimagerybyid", "label": "getImageryById()", "file_type": "code", "source_file": "src\\lib\\online\\satellite.ts", "source_location": "L121"}, {"id": "satellite_getsentinel2tileurl", "label": "getSentinel2TileUrl()", "file_type": "code", "source_file": "src\\lib\\online\\satellite.ts", "source_location": "L125"}, {"id": "satellite_calculatendvi", "label": "calculateNDVI()", "file_type": "code", "source_file": "src\\lib\\online\\satellite.ts", "source_location": "L135"}, {"id": "satellite_getimagerymetadata", "label": "getImageryMetadata()", "file_type": "code", "source_file": "src\\lib\\online\\satellite.ts", "source_location": "L152"}], "edges": [{"source": "src_lib_online_satellite_ts", "target": "satellite_getimagerylayers", "relation": "contains", "confidence": "EXTRACTED", "source_file": "src\\lib\\online\\satellite.ts", "source_location": "L73", "weight": 1.0}, {"source": "src_lib_online_satellite_ts", "target": "satellite_getimageryforlocation", "relation": "contains", "confidence": "EXTRACTED", "source_file": "src\\lib\\online\\satellite.ts", "source_location": "L85", "weight": 1.0}, {"source": "src_lib_online_satellite_ts", "target": "satellite_getimagerybyid", "relation": "contains", "confidence": "EXTRACTED", "source_file": "src\\lib\\online\\satellite.ts", "source_location": "L121", "weight": 1.0}, {"source": "src_lib_online_satellite_ts", "target": "satellite_getsentinel2tileurl", "relation": "contains", "confidence": "EXTRACTED", "source_file": "src\\lib\\online\\satellite.ts", "source_location": "L125", "weight": 1.0}, {"source": "src_lib_online_satellite_ts", "target": "satellite_calculatendvi", "relation": "contains", "confidence": "EXTRACTED", "source_file": "src\\lib\\online\\satellite.ts", "source_location": "L135", "weight": 1.0}, {"source": "src_lib_online_satellite_ts", "target": "satellite_getimagerymetadata", "relation": "contains", "confidence": "EXTRACTED", "source_file": "src\\lib\\online\\satellite.ts", "source_location": "L152", "weight": 1.0}]}