{"nodes": [{"id": "src_lib_compute_volumerunner_ts", "label": "volumeRunner.ts", "file_type": "code", "source_file": "src\\lib\\compute\\volumeRunner.ts", "source_location": "L1"}, {"id": "volumerunner_computevolume", "label": "computeVolume()", "file_type": "code", "source_file": "src\\lib\\compute\\volumeRunner.ts", "source_location": "L17"}, {"id": "volumerunner_computecutfillvolume", "label": "computeCutFillVolume()", "file_type": "code", "source_file": "src\\lib\\compute\\volumeRunner.ts", "source_location": "L21"}, {"id": "volumerunner_getvolumesummary", "label": "getVolumeSummary()", "file_type": "code", "source_file": "src\\lib\\compute\\volumeRunner.ts", "source_location": "L25"}, {"id": "volumerunner_getcutfillsummary", "label": "getCutFillSummary()", "file_type": "code", "source_file": "src\\lib\\compute\\volumeRunner.ts", "source_location": "L35"}], "edges": [{"source": "src_lib_compute_volumerunner_ts", "target": "volume", "relation": "imports_from", "confidence": "EXTRACTED", "source_file": "src\\lib\\compute\\volumeRunner.ts", "source_location": "L1", "weight": 1.0}, {"source": "src_lib_compute_volumerunner_ts", "target": "volumerunner_computevolume", "relation": "contains", "confidence": "EXTRACTED", "source_file": "src\\lib\\compute\\volumeRunner.ts", "source_location": "L17", "weight": 1.0}, {"source": "src_lib_compute_volumerunner_ts", "target": "volumerunner_computecutfillvolume", "relation": "contains", "confidence": "EXTRACTED", "source_file": "src\\lib\\compute\\volumeRunner.ts", "source_location": "L21", "weight": 1.0}, {"source": "src_lib_compute_volumerunner_ts", "target": "volumerunner_getvolumesummary", "relation": "contains", "confidence": "EXTRACTED", "source_file": "src\\lib\\compute\\volumeRunner.ts", "source_location": "L25", "weight": 1.0}, {"source": "src_lib_compute_volumerunner_ts", "target": "volumerunner_getcutfillsummary", "relation": "contains", "confidence": "EXTRACTED", "source_file": "src\\lib\\compute\\volumeRunner.ts", "source_location": "L35", "weight": 1.0}]}