{"nodes": [{"id": "src_components_compute_crosssectionspanel_tsx", "label": "CrossSectionsPanel.tsx", "file_type": "code", "source_file": "src\\components\\compute\\CrossSectionsPanel.tsx", "source_location": "L1"}, {"id": "crosssectionspanel_crosssectionspanel", "label": "CrossSectionsPanel()", "file_type": "code", "source_file": "src\\components\\compute\\CrossSectionsPanel.tsx", "source_location": "L3"}], "edges": [{"source": "src_components_compute_crosssectionspanel_tsx", "target": "crosssectionspanel_crosssectionspanel", "relation": "contains", "confidence": "EXTRACTED", "source_file": "src\\components\\compute\\CrossSectionsPanel.tsx", "source_location": "L3", "weight": 1.0}]}